sharing/__init__.py
sharing/abstract.py
sharing/common.py
sharing/counter.py
sharing/shared.py
sharing-0.1.0.dist-info/LICENSE
sharing-0.1.0.dist-info/METADATA
sharing-0.1.0.dist-info/WHEEL
sharing-0.1.0.dist-info/top_level.txt
sharing-0.1.0.dist-info/RECORD
