Metadata-Version: 2.1
Name: sharing
Version: 0.1.0
Summary: Package allowing to share variables, configurations and counters between dependencies
Home-page: https://gitlab.guirimand.eu/tguirimand/sharing
Author: Thibaut Guirimand
Author-email: tguirimand@gmx.fr
License: UNKNOWN
Platform: UNKNOWN
Classifier: Programming Language :: Python :: 3
Classifier: Operating System :: OS Independent
Classifier: Development Status :: 3 - Alpha
Classifier: Intended Audience :: Developers
Classifier: License :: OSI Approved :: MIT License
Classifier: Topic :: Software Development
Classifier: Environment :: Plugins
Requires-Python: >=3.8
